qiskit_metal/__init__.py
qiskit_metal/_defaults.py
qiskit_metal/_gui/__compile_ui_to_py.bat
qiskit_metal/_gui/__compile_ui_to_py.shell
qiskit_metal/_gui/__init__.py
qiskit_metal/_gui/_imgs/_imgs.qrc
qiskit_metal/_gui/_imgs/browser.png
qiskit_metal/_gui/_imgs/build_history.png
qiskit_metal/_gui/_imgs/build_history_small.png
qiskit_metal/_gui/_imgs/cancel.png
qiskit_metal/_gui/_imgs/components/Cap3Interdigital.png
qiskit_metal/_gui/_imgs/components/CapNInterdigital.png
qiskit_metal/_gui/_imgs/components/CapNInterdigitalTee.png
qiskit_metal/_gui/_imgs/components/CircleCaterpillar.png
qiskit_metal/_gui/_imgs/components/CircleRaster.png
qiskit_metal/_gui/_imgs/components/CoupledLineTee.png
qiskit_metal/_gui/_imgs/components/JJ_Dolan.png
qiskit_metal/_gui/_imgs/components/JJ_Manhattan.png
qiskit_metal/_gui/_imgs/components/LaunchpadWirebond.png
qiskit_metal/_gui/_imgs/components/LaunchpadWirebondCoupled.png
qiskit_metal/_gui/_imgs/components/LineTee.png
qiskit_metal/_gui/_imgs/components/NGon.png
qiskit_metal/_gui/_imgs/components/NSquareSpiral.png
qiskit_metal/_gui/_imgs/components/Rectangle.png
qiskit_metal/_gui/_imgs/components/RectangleHollow.png
qiskit_metal/_gui/_imgs/components/ResonatorCoilRect.png
qiskit_metal/_gui/_imgs/components/SmileyFace.png
qiskit_metal/_gui/_imgs/components/Transmon_Interdigitated.png
qiskit_metal/_gui/_imgs/components/TunableCoupler01.png
qiskit_metal/_gui/_imgs/components/resonator_lumped.PNG
qiskit_metal/_gui/_imgs/components/squid_loop.png
qiskit_metal/_gui/_imgs/components/star_qubit.png
qiskit_metal/_gui/_imgs/components/transmon_concentric.png
qiskit_metal/_gui/_imgs/components/transmon_concentric_type_2.PNG
qiskit_metal/_gui/_imgs/components/transmon_cross.png
qiskit_metal/_gui/_imgs/components/transmon_cross_fl.png
qiskit_metal/_gui/_imgs/components/transmon_pocket.png
qiskit_metal/_gui/_imgs/components/transmon_pocket_6.png
qiskit_metal/_gui/_imgs/components/transmon_pocket_cl.png
quantum_metal-0.5.3.post1.dist-info/licenses/LICENSE.txt
quantum_metal-0.5.3.post1.dist-info/WHEEL
quantum_metal-0.5.3.post1.dist-info/METADATA
quantum_metal-0.5.3.post1.dist-info/RECORD
