Metadata-Version: 2.4
Name: quantum-metal
Version: 0.5.3.post1
Summary: Quantum Metal (formerly Qiskit Metal) | for quantum device design & analysis
Keywords: eda,qiskit,quantum,sdk
Author: Zlatko Minev, Thomas McConkey, IBM Quantum Team, Quantum Device Consortium (QDC)
License-Expression: Apache-2.0
License-File: LICENSE.txt
Classifier: Intended Audience :: Developers
Classifier: Intended Audience :: Science/Research
Classifier: License :: OSI Approved :: Apache Software License
Classifier: Operating System :: MacOS
Classifier: Operating System :: Microsoft :: Windows
Classifier: Operating System :: POSIX :: Linux
Classifier: Programming Language :: Python :: 3 :: Only
Classifier: Programming Language :: Python :: 3.10
Classifier: Programming Language :: Python :: 3.11
Classifier: Programming Language :: Python :: 3.12
Classifier: Topic :: Scientific/Engineering
Requires-Dist: addict>=2.4.0
Requires-Dist: gdstk>=0.9
Requires-Dist: geopandas>=1.0
Requires-Dist: matplotlib>=3.7.0
Requires-Dist: numpy>=1.24.2,<2
Requires-Dist: pandas>=2.1.1
Requires-Dist: pint>=0.21.0
Requires-Dist: pyepr-quantum>=0.9.0
Requires-Dist: pygments>=2.14.0
Requires-Dist: pyside6>=6.8
Requires-Dist: qdarkstyle>=3.1
Requires-Dist: qutip>=5.0.0
Requires-Dist: scipy>=1.10.0
Requires-Dist: shapely>=2.0.1
Requires-Dist: scqubits>=4.1.0
Requires-Dist: gmsh>=4.11.1
Requires-Dist: pyaedt>=0.21,<0.24
Requires-Dist: pyyaml>=6.0
Requires-Python: >=3.10, <3.13
Project-URL: bugtracker, https://github.com/qiskit-community/qiskit-metal/issues
Project-URL: documentation, https://qiskit-community.github.io/qiskit-metal/
Project-URL: source, https://github.com/qiskit-community/qiskit-metal
